dinao/__init__.py
dinao/__version__.py
dinao/backend/__init__.py
dinao/backend/base.py
dinao/backend/errors.py
dinao/backend/mariadb.py
dinao/backend/mysql.py
dinao/backend/postgres.py
dinao/backend/sqlite.py
dinao/binding/__init__.py
dinao/binding/binders.py
dinao/binding/errors.py
dinao/binding/mappers.py
dinao/binding/templating.py
dinao-2.0.0.dist-info/licenses/AUTHORS
dinao-2.0.0.dist-info/licenses/LICENSE
dinao-2.0.0.dist-info/METADATA
dinao-2.0.0.dist-info/WHEEL
dinao-2.0.0.dist-info/top_level.txt
dinao-2.0.0.dist-info/RECORD
